src/__init__.py
src/main.py
src/utils.py
src/addons/__init__.py
src/addons/binding.py
src/interceptor/__init__.py
src/interceptor/cache.py
src/interceptor/chain.py
src/interceptor/filte.py
src/interceptor/interceptor.py
src/interceptor/markdown.py
src/interceptor/vote.py
src/model/__init__.py
src/model/conversation.py
src/model/request.py
copilot_exporter-0.1.2.dist-info/LICENCE
copilot_exporter-0.1.2.dist-info/METADATA
copilot_exporter-0.1.2.dist-info/WHEEL
copilot_exporter-0.1.2.dist-info/top_level.txt
copilot_exporter-0.1.2.dist-info/RECORD
